.gitignore
.pre-commit-config.yaml
.readthedocs.yml
Dockerfile
LICENSE
MANIFEST.in
README.md
pyproject.toml
requirements-min.txt
requirements.txt
setup.cfg
setup.py
.github/codecov.yml
.github/env.yml
.github/workflows/testing.yml
classrad/README.md
classrad/__init__.py
classrad/get_maps.py
classrad.egg-info/PKG-INFO
classrad.egg-info/SOURCES.txt
classrad.egg-info/dependency_links.txt
classrad.egg-info/requires.txt
classrad.egg-info/top_level.txt
classrad/config/__init__.py
classrad/config/config.py
classrad/config/pyradiomics_feature_names.json
classrad/config/pyradiomics_params/Baessler_CT.yaml
classrad/config/pyradiomics_params/default_feature_map.yaml
classrad/data/__init__.py
classrad/data/dataset.py
classrad/evaluation/__init__.py
classrad/evaluation/evaluator.py
classrad/evaluation/evaluator_nnunet.py
classrad/evaluation/metrics.py
classrad/evaluation/utils.py
classrad/feature_extraction/__init__.py
classrad/feature_extraction/distance_extractor.py
classrad/feature_extraction/extractor.py
classrad/feature_selection/__init__.py
classrad/feature_selection/feature_selector.py
classrad/maps/__init__.py
classrad/maps/get_maps.py
classrad/maps/radiomics_params.yaml
classrad/maps/utils.py
classrad/maps/utils_2.py
classrad/models/__init__.py
classrad/models/classifier.py
classrad/registration/__init__.py
classrad/registration/notes.txt
classrad/segmentation/__init__.py
classrad/segmentation/utils.py
classrad/training/__init__.py
classrad/training/trainer.py
classrad/utils/__init__.py
classrad/utils/io.py
classrad/utils/preprocessing.py
classrad/utils/splitting.py
classrad/utils/statistics.py
classrad/utils/utils.py
classrad/utils/visualization.py
docs/segmentation.md
docs/images/docker.png
docs/images/logo.png
docs/images/logo_white.png
docs/images/logo_white_small.png
docs/images/python.png
docs/images/streamlit.png
tests/classrad/test_dataset.py
tests/classrad/test_utils.py
tests/testing_data/DICOM/DWI.dcm
tests/testing_data/DICOM/CT_head/CTHead1.dcm
tests/testing_data/DICOM/CT_head/CTHead10.dcm
tests/testing_data/DICOM/CT_head/CTHead11.dcm
tests/testing_data/DICOM/CT_head/CTHead12.dcm
