Metadata-Version: 2.1
Name: classrad
Version: 0.1
Summary: Radiomics-related modules for extraction and experimenting
Home-page: https://github.com/pwoznicki/ClassyRadiomics
Author: Piotr Woznicki
Author-email: piotrekwoznicki@gmail.com
License: UNKNOWN
Project-URL: Bug Tracker, https://github.com/pwoznicki/ClassyRadiomics
Platform: UNKNOWN
Classifier: Programming Language :: Python :: 3
Classifier: Operating System :: OS Independent
Requires-Python: >=3.7
License-File: LICENSE
